spreadsheet_handling/__init__.py
spreadsheet_handling/_version.py
spreadsheet_handling/logging_utils.py
spreadsheet_handling/cli/__init__.py
spreadsheet_handling/cli/run.py
spreadsheet_handling/cli/sheets_pack.py
spreadsheet_handling/cli/sheets_unpack.py
spreadsheet_handling/core/__init__.py
spreadsheet_handling/core/df_build.py
spreadsheet_handling/core/fk.py
spreadsheet_handling/core/flatten.py
spreadsheet_handling/core/indexing.py
spreadsheet_handling/core/paths.py
spreadsheet_handling/core/refs.py
spreadsheet_handling/core/unflatten.py
spreadsheet_handling/domain/extractions/__init__.py
spreadsheet_handling/domain/transformations/__init__.py
spreadsheet_handling/domain/transformations/helpers.py
spreadsheet_handling/domain/validations/__init__.py
spreadsheet_handling/engine/__init__.py
spreadsheet_handling/engine/config.py
spreadsheet_handling/engine/orchestrator.py
spreadsheet_handling/examples/pipeline_basic.yml
spreadsheet_handling/examples/pipeline_pack.yml
spreadsheet_handling/examples/pipelines.yml
spreadsheet_handling/io_backends/__init__.py
spreadsheet_handling/io_backends/base.py
spreadsheet_handling/io_backends/csv_backend.py
spreadsheet_handling/io_backends/excel_xlsxwriter.py
spreadsheet_handling/io_backends/json_backend.py
spreadsheet_handling/io_backends/ods_backend.py
spreadsheet_handling/io_backends/router.py
spreadsheet_handling/io_backends/xlsx_backend.py
spreadsheet_handling/io_backends/yaml_backend.py
spreadsheet_handling/pipeline/__init__.py
spreadsheet_handling/pipeline/config.py
spreadsheet_handling/pipeline/pipeline.py
spreadsheet_handling/pipeline/runner.py
spreadsheet_handling/pipeline/types.py
spreadsheet_handling-0.1.0b4.dist-info/licenses/LICENSE
spreadsheet_handling-0.1.0b4.dist-info/METADATA
spreadsheet_handling-0.1.0b4.dist-info/WHEEL
spreadsheet_handling-0.1.0b4.dist-info/entry_points.txt
spreadsheet_handling-0.1.0b4.dist-info/top_level.txt
spreadsheet_handling-0.1.0b4.dist-info/RECORD
