Metadata-Version: 2.4
Name: spreadsheet-handling
Version: 0.1.0b4
Summary: Composable pipelines for spreadsheets (JSON/YAML/CSV/XLSX) with FK helpers, validation, and IO routing.
Author: Stefan Schade
License: MIT License
Project-URL: Homepage, https://github.com/StefanSchade/spreadsheet-handling
Project-URL: Issues, https://github.com/StefanSchade/spreadsheet-handling/issues
Classifier: Programming Language :: Python :: 3
Classifier: Operating System :: OS Independent
Requires-Python: >=3.10
License-File: LICENSE
Requires-Dist: pandas>=2.0
Requires-Dist: openpyxl>=3.1
Requires-Dist: XlsxWriter>=3.0
Requires-Dist: pyyaml>=6
Provides-Extra: dev
Requires-Dist: pytest>=8; extra == "dev"
Requires-Dist: pytest-cov>=5; extra == "dev"
Requires-Dist: ruff>=0.4; extra == "dev"
Requires-Dist: black>=24; extra == "dev"
Requires-Dist: autopep8>=2; extra == "dev"
Provides-Extra: ods
Requires-Dist: odfpy>=1.4.1; extra == "ods"
Dynamic: license-file
